Workbook

Sheet PORTADA
B2: MATRIZ DE TRAZABILIDAD RUP SISTEMA INTEGRAL DE GESTIÓN PARA RESTAURANTE
B4: Proceso Unificado Rational (RUP) · SRS v2.0 · CU v2.0 · BPMN v2.0 · UML v2.0
B6: Nombre del Proyecto | C6: Sistema Integral de Gestión para Restaurante
B7: Código del Proyecto | C7: PROY-REST-001
B8: Empresa / Cliente | C8: Restaurante [Nombre del Restaurante] — Guatemala
B9: Versión del Documento | C9: 2.0
B10: Elaborado por | C10: Equipo de Proyecto / Análisis
B11: Revisado por | C11: [Completar]
B12: Fecha de Elaboración | C12: 16/08/2026
B13: Estado | C13: Documento de trazabilidad actualizado — pendiente de validación de stakeholders
B16: LEYENDA DE ESTADOS
B17: ✅ Documentado / Trazado | C17: El artefacto o vínculo existe y está documentado en la versión 2.0.
B18: 🧪 Planificado | C18: Caso de prueba identificado, todavía no ejecutado.
B19: ⚠ Validar brecha v2.0 | C19: Requerimiento complementario agregado por análisis técnico y sujeto a aprobación.
B20: ⏳ Pendiente | C20: Implementación, validación o artefacto todavía pendiente.
B21: 🔄 En Progreso | C21: Actividad actualmente en desarrollo o validación.
B22: ✅ Verificado | C22: Implementado y validado satisfactoriamente.
B24: CONTENIDO DEL ARCHIVO
B25: RF → CU | C25: Trazabilidad completa de los 131 RF con sus 131 Casos de Uso.
B26: RF → RNF | C26: Mapeo de RF a los 22 RNF aplicables (783 vínculos documentales).
B27: RF → CP | C27: 131 Casos de Prueba base planificados, uno por RF, con precondición y resultado esperado.
B28: RF → BPMN | C28: Trazabilidad de cada RF/CU con el proceso BPMN del módulo correspondiente.
B29: MATRIZ COMPLETA | C29: Vista consolidada RF ↔ CU ↔ RNF ↔ CP, prioridad y estado documental.
B30: RESUMEN ESTADO | C30: Dashboard de cobertura, distribución por módulo y KPIs del proyecto.
B31: CATÁLOGO RNF | C31: Catálogo completo de 22 RNF, categoría ISO/IEC 25010 y prioridad propuesta.
B32: MÓDULOS | C32: Catálogo de 17 módulos con conteo RF base / complementarios v2.0.
B33: PENDIENTES RUP | C33: Riesgos, decisiones abiertas y artefactos pendientes/actualizados.
B35: NOTAS DE USO
B36: 1. La matriz refleja cobertura documental y trazabilidad; no debe interpretarse como evidencia de que el software ya fue implementado.
B37: 2. Los 30 RF identificados como “brecha v2.0” requieren validación formal de stakeholders antes de fijar línea base.
B38: 3. Los 131 CP son casos base planificados. Deben desglosarse en escenarios positivos, negativos, límites, integración, seguridad y rendimiento durante QA.
B39: 4. La prioridad de los RNF es una propuesta de planificación técnica y debe confirmarse con negocio, arquitectura y QA.

Sheet RF → CU
A1: TRAZABILIDAD — REQUERIMIENTOS FUNCIONALES ↔ CASOS DE USO
A2: Sistema Integral de Gestión para Restaurante · 131 RF ↔ 131 CU · Versión 2.0
A3: ID Requerimiento Funcional | B3: Nombre del RF | C3: Módulo / Subsistema | D3: ID Caso de Uso | E3: Nombre del Caso de Uso | F3: Actor Principal | G3: Prioridad RF | H3: Estado Trazabilidad | I3: Observaciones
A4: RF-AUTH-001-BASICO | B4: Inicio de sesión con usuario y contraseña | C4: Autenticación y Control de Acceso | D4: CU-AUTH-001-BASICO | E4: Inicio de sesión con usuario y contraseña | F4: Todos los roles del sistema | G4: Alta | H4: ✅ Trazado | I4: Base original (v1.0 normalizada) · Estado SRS: Por desarrollar · Dependencias: RF-AUTH-009
A5: RF-AUTH-002-BASICO | B5: Recuperación de contraseña vía correo | C5: Autenticación y Control de Acceso | D5: CU-AUTH-002-BASICO | E5: Recuperación de contraseña vía correo | F5: Todos los roles | G5: Media | H5: ✅ Trazado | I5: Base original (v1.0 normalizada) · Estado SRS: Por desarrollar · Dependencias: RF-AUTH-001-BASICO
A6: RF-AUTH-003-PREMIUM | B6: Autenticación de dos factores (2FA) | C6: Autenticación y Control de Acceso | D6: CU-AUTH-003-PREMIUM | E6: Autenticación de dos factores (2FA) | F6: Administrador | G6: Alta | H6: ✅ Trazado | I6: Base original (v1.0 normalizada) · Estado SRS: Por desarrollar · Dependencias: RF-AUTH-001-BASICO
A7: RF-AUTH-004-PREMIUM | B7: Códigos de respaldo de un solo uso | C7: Autenticación y Control de Acceso | D7: CU-AUTH-004-PREMIUM | E7: Códigos de respaldo de un solo uso | F7: Administrador | G7: Media | H7: ✅ Trazado | I7: Base original (v1.0 normalizada) · Estado SRS: Por desarrollar · Dependencias: RF-AUTH-003-PREMIUM
A8: RF-AUTH-005-PREMIUM | B8: Bitácora de auditoría de inicios de sesión | C8: Autenticación y Control de Acceso | D8: CU-AUTH-005-PREMIUM | E8: Bitácora de auditoría de inicios de sesión | F8: Administrador | G8: Media | H8: ✅ Trazado | I8: Base original (v1.0 normalizada) · Estado SRS: Por desarrollar · Dependencias: RF-AUTH-001-BASICO
A9: RF-AUTH-006-GOLD | B9: Autenticación biométrica (WebAuthn/FIDO2) | C9: Autenticación y Control de Acceso | D9: CU-AUTH-006-GOLD | E9: Autenticación biométrica (WebAuthn/FIDO2) | F9: Administrador | G9: Baja | H9: ✅ Trazado | I9: Base original (v1.0 normalizada) · Estado SRS: Por desarrollar · Dependencias: RF-AUTH-001-BASICO
A10: RF-AUTH-007-GOLD | B10: Soporte de llave de seguridad física (Hardware Key) | C10: Autenticación y Control de Acceso | D10: CU-AUTH-007-GOLD | E10: Soporte de llave de seguridad física (Hardware Key) | F10: Administrador | G10: Baja | H10: ✅ Trazado | I10: Base original (v1.0 normalizada) · Estado SRS: Por desarrollar · Dependencias: RF-AUTH-001-BASICO
A11: RF-AUTH-008-GOLD | B11: Gestión de dispositivos confiables | C11: Autenticación y Control de Acceso | D11: CU-AUTH-008-GOLD | E11: Gestión de dispositivos confiables | F11: Administrador | G11: Media | H11: ✅ Trazado | I11: Base original (v1.0 normalizada) · Estado SRS: Por desarrollar · Dependencias: RF-AUTH-003-PREMIUM
A12: RF-AUTH-009 | B12: Expiración de sesión por inactividad | C12: Autenticación y Control de Acceso | D12: CU-AUTH-009 | E12: Expiración de sesión por inactividad | F12: Todos los roles | G12: Alta | H12: ✅ Trazado | I12: Base original (v1.0 normalizada) · Estado SRS: Por desarrollar
A13: RF-REG-001-BASICO | B13: Registro de datos personales del empleado | C13: Registro y Gestión de Personal | D13: CU-REG-001-BASICO | E13: Registro de datos personales del empleado | F13: Administrador | G13: Alta | H13: ✅ Trazado | I13: Base original (v1.0 normalizada) · Estado SRS: Por desarrollar
A14: RF-REG-002-BASICO | B14: Control de acceso administrativo único | C14: Registro y Gestión de Personal | D14: CU-REG-002-BASICO | E14: Control de acceso administrativo único | F14: Administrador | G14: Media | H14: ✅ Trazado | I14: Base original (v1.0 normalizada) · Estado SRS: Por desarrollar · Dependencias: RF-AUTH-001-BASICO
... A134: RF-CFG-004 | B134: Plantillas de notificación y canales | C134: Configuración, Sucursales e Integraciones | D134: CU-CFG-004 | E134: Plantillas de notificación y canales | F134: Administrador | G134: Media | H134: ⚠ Validar brecha v2.0 | I134: Análisis de brecha v2.0 · Estado SRS: Propuesto para validación · Dependencias: RF-RES-005, RF-CRM-006

Sheet RF → RNF
A1: TRAZABILIDAD — REQUERIMIENTOS FUNCIONALES ↔ NO FUNCIONALES
A2: Mapeo de 131 RF con 22 RNF · 783 vínculos documentales · Versión 2.0
A3: ID RF | B3: Nombre RF | C3: ID RNF | D3: Nombre RNF | E3: Categoría ISO/IEC 25010 | F3: Descripción del Vínculo | G3: Prioridad RF | H3: Prioridad RNF | I3: Estado Enlace RF | J3: Estado RNF | K3: Observaciones
A4: RF-AUTH-001-BASICO | B4: Inicio de sesión con usuario y contraseña | C4: RNF-002 | D4: Seguridad | E4: Seguridad | F4: El RF RF-AUTH-001-BASICO debe observar seguridad dentro del módulo Autenticación y Control de Acceso y validarse junto con el criterio de aceptación del RF/CU. | G4: Alta | H4: Alta | I4: ✅ Trazado | J4: ⏳ Pendiente | K4: Mapeo alineado con Casos de Uso v2.0.
A5: RF-AUTH-001-BASICO | B5: Inicio de sesión con usuario y contraseña | C5: RNF-010 | D5: Auditabilidad | E5: Seguridad | F5: El RF RF-AUTH-001-BASICO debe observar auditabilidad dentro del módulo Autenticación y Control de Acceso y validarse junto con el criterio de aceptación del RF/CU. | G5: Alta | H5: Alta | I5: ✅ Trazado | J5: ⏳ Pendiente | K5: Mapeo alineado con Casos de Uso v2.0.
A6: RF-AUTH-001-BASICO | B6: Inicio de sesión con usuario y contraseña | C6: RNF-013 | D6: Observabilidad | E6: Mantenibilidad / Fiabilidad | F6: El RF RF-AUTH-001-BASICO debe observar observabilidad dentro del módulo Autenticación y Control de Acceso y validarse junto con el criterio de aceptación del RF/CU. | G6: Alta | H6: Alta | I6: ✅ Trazado | J6: ⏳ Pendiente | K6: Mapeo alineado con Casos de Uso v2.0.
A7: RF-AUTH-001-BASICO | B7: Inicio de sesión con usuario y contraseña | C7: RNF-019 | D7: Retención y Archivo | E7: Seguridad / Fiabilidad | F7: El RF RF-AUTH-001-BASICO debe observar retención y archivo dentro del módulo Autenticación y Control de Acceso y validarse junto con el criterio de aceptación del RF/CU. | G7: Alta | H7: Media | I7: ✅ Trazado | J7: ⏳ Pendiente | K7: Mapeo alineado con Casos de Uso v2.0.
A8: RF-AUTH-001-BASICO | B8: Inicio de sesión con usuario y contraseña | C8: RNF-022 | D8: Segregación de Datos Multi-sucursal | E8: Seguridad | F8: El RF RF-AUTH-001-BASICO debe observar segregación de datos multi-sucursal dentro del módulo Autenticación y Control de Acceso y validarse junto con el criterio de aceptación del RF/CU. | G8: Alta | H8: Alta | I8: ✅ Trazado | J8: ⏳ Pendiente | K8: Mapeo alineado con Casos de Uso v2.0.
A9: RF-AUTH-002-BASICO | B9: Recuperación de contraseña vía correo | C9: RNF-002 | D9: Seguridad | E9: Seguridad | F9: El RF RF-AUTH-002-BASICO debe observar seguridad dentro del módulo Autenticación y Control de Acceso y validarse junto con el criterio de aceptación del RF/CU. | G9: Media | H9: Alta | I9: ✅ Trazado | J9: ⏳ Pendiente | K9: Mapeo alineado con Casos de Uso v2.0.
A10: RF-AUTH-002-BASICO | B10: Recuperación de contraseña vía correo | C10: RNF-010 | D10: Auditabilidad | E10: Seguridad | F10: El RF RF-AUTH-002-BASICO debe observar auditabilidad dentro del módulo Autenticación y Control de Acceso y validarse junto con el criterio de aceptación del RF/CU. | G10: Media | H10: Alta | I10: ✅ Trazado | J10: ⏳ Pendiente | K10: Mapeo alineado con Casos de Uso v2.0.
A11: RF-AUTH-002-BASICO | B11: Recuperación de contraseña vía correo | C11: RNF-013 | D11: Observabilidad | E11: Mantenibilidad / Fiabilidad | F11: El RF RF-AUTH-002-BASICO debe observar observabilidad dentro del módulo Autenticación y Control de Acceso y validarse junto con el criterio de aceptación del RF/CU. | G11: Media | H11: Alta | I11: ✅ Trazado | J11: ⏳ Pendiente | K11: Mapeo alineado con Casos de Uso v2.0.
A12: RF-AUTH-002-BASICO | B12: Recuperación de contraseña vía correo | C12: RNF-019 | D12: Retención y Archivo | E12: Seguridad / Fiabilidad | F12: El RF RF-AUTH-002-BASICO debe observar retención y archivo dentro del módulo Autenticación y Control de Acceso y validarse junto con el criterio de aceptación del RF/CU. | G12: Media | H12: Media | I12: ✅ Trazado | J12: ⏳ Pendiente | K12: Mapeo alineado con Casos de Uso v2.0.
A13: RF-AUTH-002-BASICO | B13: Recuperación de contraseña vía correo | C13: RNF-022 | D13: Segregación de Datos Multi-sucursal | E13: Seguridad | F13: El RF RF-AUTH-002-BASICO debe observar segregación de datos multi-sucursal dentro del módulo Autenticación y Control de Acceso y validarse junto con el criterio de aceptación del RF/CU. | G13: Media | H13: Alta | I13: ✅ Trazado | J13: ⏳ Pendiente | K13: Mapeo alineado con Casos de Uso v2.0.
A14: RF-AUTH-003-PREMIUM | B14: Autenticación de dos factores (2FA) | C14: RNF-002 | D14: Seguridad | E14: Seguridad | F14: El RF RF-AUTH-003-PREMIUM debe observar seguridad dentro del módulo Autenticación y Control de Acceso y validarse junto con el criterio de aceptación del RF/CU. | G14: Alta | H14: Alta | I14: ✅ Trazado | J14: ⏳ Pendiente | K14: Mapeo alineado con Casos de Uso v2.0.
... A786: RF-CFG-004 | B786: Plantillas de notificación y canales | C786: RNF-022 | D786: Segregación de Datos Multi-sucursal | E786: Seguridad | F786: El RF RF-CFG-004 debe observar segregación de datos multi-sucursal dentro del módulo Configuración, Sucursales e Integraciones y validarse junto con el criterio de aceptación del RF/CU. | G786: Media | H786: Alta | I786: ✅ Trazado | J786: ⏳ Pendiente | K786: Mapeo alineado con Casos de Uso v2.0.

Sheet RF → CP
A1: TRAZABILIDAD — REQUERIMIENTOS FUNCIONALES ↔ CASOS DE PRUEBA
A2: 131 Casos de Prueba base planificados · Criterios derivados del SRS/CU v2.0
A3: ID RF | B3: Nombre RF | C3: ID Caso de Prueba | D3: Nombre del Caso de Prueba | E3: Tipo de Prueba | F3: Precondición | G3: Datos de Entrada | H3: Resultado Esperado | I3: Resultado Obtenido | J3: Prioridad | K3: Estado | L3: Responsable QA | M3: Observaciones
A4: RF-AUTH-001-BASICO | B4: Inicio de sesión con usuario y contraseña | C4: CP-AUTH-001-BASICO | D4: Validar — Inicio de sesión con usuario y contraseña | E4: Seguridad / Funcional | F4: Cuenta activa/habilitada; servicio de autenticación disponible. | G4: Usuario/correo, contraseña | H4: Un usuario con credenciales válidas accede al sistema; con credenciales inválidas se muestra error sin revelar cuál campo falló. | I4: Pendiente de ejecución | J4: Alta | K4: 🧪 Planificado | L4: Por asignar | M4: CP base de trazabilidad. Desglosar casos positivos, negativos y de borde en el plan de pruebas.
A5: RF-AUTH-002-BASICO | B5: Recuperación de contraseña vía correo | C5: CP-AUTH-002-BASICO | D5: Validar — Recuperación de contraseña vía correo | E5: Seguridad / Funcional | F5: Cuenta registrada y acceso al correo/canal de recuperación aprobado; no requiere sesión iniciada. | G5: Correo electrónico registrado | H5: El usuario puede definir una nueva contraseña siguiendo el enlace recibido antes de su expiración. | I5: Pendiente de ejecución | J5: Media | K5: 🧪 Planificado | L5: Por asignar | M5: CP base de trazabilidad. Desglosar casos positivos, negativos y de borde en el plan de pruebas.
A6: RF-AUTH-003-PREMIUM | B6: Autenticación de dos factores (2FA) | C6: CP-AUTH-003-PREMIUM | D6: Validar — Autenticación de dos factores (2FA) | E6: Seguridad / Funcional | F6: Actor autenticado con permisos del módulo AUTH. Datos maestros y configuraciones dependientes vigentes. | G6: Código OTP de 6 dígitos | H6: El acceso solo se concede tras validar correctamente usuario/contraseña y el código de segundo factor. | I6: Pendiente de ejecución | J6: Alta | K6: 🧪 Planificado | L6: Por asignar | M6: CP base de trazabilidad. Desglosar casos positivos, negativos y de borde en el plan de pruebas.
A7: RF-AUTH-004-PREMIUM | B7: Códigos de respaldo de un solo uso | C7: CP-AUTH-004-PREMIUM | D7: Validar — Códigos de respaldo de un solo uso | E7: Seguridad / Funcional | F7: Actor autenticado con permisos del módulo AUTH. Datos maestros y configuraciones dependientes vigentes. | G7: Solicitud de generación | H7: Un código de respaldo usado no puede reutilizarse en un segundo intento. | I7: Pendiente de ejecución | J7: Media | K7: 🧪 Planificado | L7: Por asignar | M7: CP base de trazabilidad. Desglosar casos positivos, negativos y de borde en el plan de pruebas.
A8: RF-AUTH-005-PREMIUM | B8: Bitácora de auditoría de inicios de sesión | C8: CP-AUTH-005-PREMIUM | D8: Validar — Bitácora de auditoría de inicios de sesión | E8: Seguridad / Funcional | F8: Actor autenticado con permisos del módulo AUTH. Datos maestros y configuraciones dependientes vigentes. | G8: N/A (automático) | H8: El administrador puede consultar el historial de accesos de cualquier usuario. | I8: Pendiente de ejecución | J8: Media | K8: 🧪 Planificado | L8: Por asignar | M8: CP base de trazabilidad. Desglosar casos positivos, negativos y de borde en el plan de pruebas.
A9: RF-AUTH-006-GOLD | B9: Autenticación biométrica (WebAuthn/FIDO2) | C9: CP-AUTH-006-GOLD | D9: Validar — Autenticación biométrica (WebAuthn/FIDO2) | E9: Seguridad / Funcional | F9: Actor autenticado con permisos del módulo AUTH. Datos maestros y configuraciones dependientes vigentes. | G9: Biometría del dispositivo | H9: El usuario accede exitosamente usando huella o rostro en un dispositivo compatible sin usar contraseña. | I9: Pendiente de ejecución | J9: Baja | K9: 🧪 Planificado | L9: Por asignar | M9: CP base de trazabilidad. Desglosar casos positivos, negativos y de borde en el plan de pruebas.
A10: RF-AUTH-007-GOLD | B10: Soporte de llave de seguridad física (Hardware Key) | C10: CP-AUTH-007-GOLD | D10: Validar — Soporte de llave de seguridad física (Hardware Key) | E10: Seguridad / Funcional | F10: Actor autenticado con permisos del módulo AUTH. Datos maestros y configuraciones dependientes vigentes. | G10: Llave física conectada | H10: El sistema reconoce y valida la llave física registrada previamente. | I10: Pendiente de ejecución | J10: Baja | K10: 🧪 Planificado | L10: Por asignar | M10: CP base de trazabilidad. Desglosar casos positivos, negativos y de borde en el plan de pruebas.
A11: RF-AUTH-008-GOLD | B11: Gestión de dispositivos confiables | C11: CP-AUTH-008-GOLD | D11: Validar — Gestión de dispositivos confiables | E11: Seguridad / Funcional | F11: Actor autenticado con permisos del módulo AUTH. Datos maestros y configuraciones dependientes vigentes. | G11: Selección de dispositivo a revocar | H11: Al revocar un dispositivo, este pierde el acceso simplificado inmediatamente. | I11: Pendiente de ejecución | J11: Media | K11: 🧪 Planificado | L11: Por asignar | M11: CP base de trazabilidad. Desglosar casos positivos, negativos y de borde en el plan de pruebas.
A12: RF-AUTH-009 | B12: Expiración de sesión por inactividad | C12: CP-AUTH-009 | D12: Validar — Expiración de sesión por inactividad | E12: Seguridad / Funcional | F12: Existe un evento/transacción válido que dispara el proceso. | G12: N/A (automático) | H12: Tras el tiempo definido sin actividad, el sistema solicita reautenticación. | I12: Pendiente de ejecución | J12: Alta | K12: 🧪 Planificado | L12: Por asignar | M12: CP base de trazabilidad. Desglosar casos positivos, negativos y de borde en el plan de pruebas.
A13: RF-REG-001-BASICO | B13: Registro de datos personales del empleado | C13: CP-REG-001-BASICO | D13: Validar — Registro de datos personales del empleado | E13: Funcional / Seguridad de datos | F13: Actor autenticado con permisos del módulo REG. Sucursal/canal operativo activo cuando aplica. | G13: Datos personales del empleado | H13: Un nuevo empleado queda disponible en el sistema con todos los campos obligatorios completos. | I13: Pendiente de ejecución | J13: Alta | K13: 🧪 Planificado | L13: Por asignar | M13: CP base de trazabilidad. Desglosar casos positivos, negativos y de borde en el plan de pruebas.
A14: RF-REG-002-BASICO | B14: Control de acceso administrativo único | C14: CP-REG-002-BASICO | D14: Validar — Control de acceso administrativo único | E14: Funcional / Seguridad de datos | F14: Actor autenticado con permisos del módulo REG. Sucursal/canal operativo activo cuando aplica. Datos maestros y configuraciones dependientes vigentes. | G14: N/A | H14: Usuarios no administradores no pueden acceder al módulo de personal. | I14: Pendiente de ejecución | J14: Media | K14: 🧪 Planificado | L14: Por asignar | M14: CP base de trazabilidad. Desglosar casos positivos, negativos y de borde en el plan de pruebas.
... A134: RF-CFG-004 | B134: Plantillas de notificación y canales | C134: CP-CFG-004 | D134: Validar — Plantillas de notificación y canales | E134: Funcional | F134: Actor autenticado con permisos del módulo CFG. Sucursal/canal operativo activo cuando aplica. Datos maestros y configuraciones dependientes vigentes. | G134: Plantilla, canal, variables | H134: Antes de activar una plantilla, el sistema valida variables requeridas y permite una vista previa; los envíos quedan vinculados a la plantilla usada. | I134: Pendiente de ejecución | J134: Media | K134: 🧪 Planificado | L134: Por asignar | M134: CP base de trazabilidad. Desglosar casos positivos, negativos y de borde en el plan de pruebas.

Sheet MATRIZ COMPLETA
A1: MATRIZ DE TRAZABILIDAD COMPLETA — VISTA CONSOLIDADA
A2: RF = Requerimiento Funcional · CU = Caso de Uso · RNF = No Funcional · CP = Caso de Prueba · BPMN en observaciones
A3: ID RF | B3: Nombre RF | C3: Módulo | D3: Prioridad RF | E3: ID Caso de Uso | F3: ID RNF relacionados | G3: Categorías RNF | H3: ID Caso de Prueba | I3: Tipo de Prueba | J3: Estado RF | K3: Estado CU | L3: Estado CP | M3: Observaciones
A4: RF-AUTH-001-BASICO | B4: Inicio de sesión con usuario y contraseña | C4: Autenticación y Control de Acceso | D4: Alta | E4: CU-AUTH-001-BASICO | F4: RNF-002, RNF-010, RNF-013, RNF-019, RNF-022 | G4: Seguridad, Auditabilidad, Observabilidad, Retención y Archivo, Segregación de Datos Multi-sucursal | H4: CP-AUTH-001-BASICO | I4: Seguridad / Funcional | J4: ✅ Documentado | K4: ✅ Documentado | L4: 🧪 Planificado | M4: Base original (v1.0 normalizada) · BPMN-AUTH-001 · Dependencias: RF-AUTH-009
A5: RF-AUTH-002-BASICO | B5: Recuperación de contraseña vía correo | C5: Autenticación y Control de Acceso | D5: Media | E5: CU-AUTH-002-BASICO | F5: RNF-002, RNF-010, RNF-013, RNF-019, RNF-022 | G5: Seguridad, Auditabilidad, Observabilidad, Retención y Archivo, Segregación de Datos Multi-sucursal | H5: CP-AUTH-002-BASICO | I5: Seguridad / Funcional | J5: ✅ Documentado | K5: ✅ Documentado | L5: 🧪 Planificado | M5: Base original (v1.0 normalizada) · BPMN-AUTH-001 · Dependencias: RF-AUTH-001-BASICO
A6: RF-AUTH-003-PREMIUM | B6: Autenticación de dos factores (2FA) | C6: Autenticación y Control de Acceso | D6: Alta | E6: CU-AUTH-003-PREMIUM | F6: RNF-002, RNF-010, RNF-013, RNF-019, RNF-022 | G6: Seguridad, Auditabilidad, Observabilidad, Retención y Archivo, Segregación de Datos Multi-sucursal | H6: CP-AUTH-003-PREMIUM | I6: Seguridad / Funcional | J6: ✅ Documentado | K6: ✅ Documentado | L6: 🧪 Planificado | M6: Base original (v1.0 normalizada) · BPMN-AUTH-001 · Dependencias: RF-AUTH-001-BASICO
A7: RF-AUTH-004-PREMIUM | B7: Códigos de respaldo de un solo uso | C7: Autenticación y Control de Acceso | D7: Media | E7: CU-AUTH-004-PREMIUM | F7: RNF-002, RNF-010, RNF-013, RNF-019, RNF-022 | G7: Seguridad, Auditabilidad, Observabilidad, Retención y Archivo, Segregación de Datos Multi-sucursal | H7: CP-AUTH-004-PREMIUM | I7: Seguridad / Funcional | J7: ✅ Documentado | K7: ✅ Documentado | L7: 🧪 Planificado | M7: Base original (v1.0 normalizada) · BPMN-AUTH-001 · Dependencias: RF-AUTH-003-PREMIUM
A8: RF-AUTH-005-PREMIUM | B8: Bitácora de auditoría de inicios de sesión | C8: Autenticación y Control de Acceso | D8: Media | E8: CU-AUTH-005-PREMIUM | F8: RNF-002, RNF-010, RNF-013, RNF-019, RNF-022 | G8: Seguridad, Auditabilidad, Observabilidad, Retención y Archivo, Segregación de Datos Multi-sucursal | H8: CP-AUTH-005-PREMIUM | I8: Seguridad / Funcional | J8: ✅ Documentado | K8: ✅ Documentado | L8: 🧪 Planificado | M8: Base original (v1.0 normalizada) · BPMN-AUTH-001 · Dependencias: RF-AUTH-001-BASICO
A9: RF-AUTH-006-GOLD | B9: Autenticación biométrica (WebAuthn/FIDO2) | C9: Autenticación y Control de Acceso | D9: Baja | E9: CU-AUTH-006-GOLD | F9: RNF-002, RNF-010, RNF-013, RNF-019, RNF-022 | G9: Seguridad, Auditabilidad, Observabilidad, Retención y Archivo, Segregación de Datos Multi-sucursal | H9: CP-AUTH-006-GOLD | I9: Seguridad / Funcional | J9: ✅ Documentado | K9: ✅ Documentado | L9: 🧪 Planificado | M9: Base original (v1.0 normalizada) · BPMN-AUTH-001 · Dependencias: RF-AUTH-001-BASICO
A10: RF-AUTH-007-GOLD | B10: Soporte de llave de seguridad física (Hardware Key) | C10: Autenticación y Control de Acceso | D10: Baja | E10: CU-AUTH-007-GOLD | F10: RNF-002, RNF-010, RNF-013, RNF-019, RNF-022 | G10: Seguridad, Auditabilidad, Observabilidad, Retención y Archivo, Segregación de Datos Multi-sucursal | H10: CP-AUTH-007-GOLD | I10: Seguridad / Funcional | J10: ✅ Documentado | K10: ✅ Documentado | L10: 🧪 Planificado | M10: Base original (v1.0 normalizada) · BPMN-AUTH-001 · Dependencias: RF-AUTH-001-BASICO
A11: RF-AUTH-008-GOLD | B11: Gestión de dispositivos confiables | C11: Autenticación y Control de Acceso | D11: Media | E11: CU-AUTH-008-GOLD | F11: RNF-002, RNF-010, RNF-013, RNF-019, RNF-022 | G11: Seguridad, Auditabilidad, Observabilidad, Retención y Archivo, Segregación de Datos Multi-sucursal | H11: CP-AUTH-008-GOLD | I11: Seguridad / Funcional | J11: ✅ Documentado | K11: ✅ Documentado | L11: 🧪 Planificado | M11: Base original (v1.0 normalizada) · BPMN-AUTH-001 · Dependencias: RF-AUTH-003-PREMIUM
A12: RF-AUTH-009 | B12: Expiración de sesión por inactividad | C12: Autenticación y Control de Acceso | D12: Alta | E12: CU-AUTH-009 | F12: RNF-002, RNF-010, RNF-013, RNF-019, RNF-022 | G12: Seguridad, Auditabilidad, Observabilidad, Retención y Archivo, Segregación de Datos Multi-sucursal | H12: CP-AUTH-009 | I12: Seguridad / Funcional | J12: ✅ Documentado | K12: ✅ Documentado | L12: 🧪 Planificado | M12: Base original (v1.0 normalizada) · BPMN-AUTH-001 · Dependencias: N/A
A13: RF-REG-001-BASICO | B13: Registro de datos personales del empleado | C13: Registro y Gestión de Personal | D13: Alta | E13: CU-REG-001-BASICO | F13: RNF-002, RNF-010, RNF-014, RNF-019, RNF-022 | G13: Seguridad, Auditabilidad, Privacidad y Minimización, Retención y Archivo, Segregación de Datos Multi-sucursal | H13: CP-REG-001-BASICO | I13: Funcional / Seguridad de datos | J13: ✅ Documentado | K13: ✅ Documentado | L13: 🧪 Planificado | M13: Base original (v1.0 normalizada) · BPMN-REG-001 · Dependencias: N/A
A14: RF-REG-002-BASICO | B14: Control de acceso administrativo único | C14: Registro y Gestión de Personal | D14: Media | E14: CU-REG-002-BASICO | F14: RNF-002, RNF-010, RNF-014, RNF-019, RNF-022 | G14: Seguridad, Auditabilidad, Privacidad y Minimización, Retención y Archivo, Segregación de Datos Multi-sucursal | H14: CP-REG-002-BASICO | I14: Funcional / Seguridad de datos | J14: ✅ Documentado | K14: ✅ Documentado | L14: 🧪 Planificado | M14: Base original (v1.0 normalizada) · BPMN-REG-001 · Dependencias: RF-AUTH-001-BASICO
... A134: RF-CFG-004 | B134: Plantillas de notificación y canales | C134: Configuración, Sucursales e Integraciones | D134: Media | E134: CU-CFG-004 | F134: RNF-002, RNF-010, RNF-013, RNF-017, RNF-019, RNF-022 | G134: Seguridad, Auditabilidad, Observabilidad, Localización y Precisión Monetaria, Retención y Archivo, Segregación de Datos Multi-sucursal | H134: CP-CFG-004 | I134: Funcional | J134: ⚠ Validar brecha v2.0 | K134: ✅ Documentado | L134: 🧪 Planificado | M134: Análisis de brecha v2.0 · BPMN-CFG-001 · Dependencias: RF-RES-005, RF-CRM-006

Sheet RESUMEN ESTADO
B1: RESUMEN DE ESTADO Y COBERTURA — MATRIZ RUP v2.0
B2: Cobertura documental de 131 RF · 131 CU · 22 RNF · 131 CP base · 17 módulos BPMN
B4: Categoría / Módulo | C4: Total RF | D4: Con CU | E4: Con RNF | F4: Con CP | G4: % Cobertura
B5: Autenticación y Control de Acceso | C5: =COUNTIF('MATRIZ COMPLETA'!$C$4:$C$134,B5) -> 12 | D5: =COUNTIFS('MATRIZ COMPLETA'!$C$4:$C$134,B5,'MATRIZ COMPLETA'!$E$4:$E$134,"<>") -> 12 | E5: =COUNTIFS('MATRIZ COMPLETA'!$C$4:$C$134,B5,'MATRIZ COMPLETA'!$F$4:$F$134,"<>") -> 12 | F5: =COUNTIFS('MATRIZ COMPLETA'!$C$4:$C$134,B5,'MATRIZ COMPLETA'!$H$4:$H$134,"<>") -> 12 | G5: =IF(C5=0,0,(D5+E5+F5)/(C5*3)) -> 1
B6: Registro y Gestión de Personal | C6: =COUNTIF('MATRIZ COMPLETA'!$C$4:$C$134,B6) -> 5 | D6: =COUNTIFS('MATRIZ COMPLETA'!$C$4:$C$134,B6,'MATRIZ COMPLETA'!$E$4:$E$134,"<>") -> 5 | E6: =COUNTIFS('MATRIZ COMPLETA'!$C$4:$C$134,B6,'MATRIZ COMPLETA'!$F$4:$F$134,"<>") -> 5 | F6: =COUNTIFS('MATRIZ COMPLETA'!$C$4:$C$134,B6,'MATRIZ COMPLETA'!$H$4:$H$134,"<>") -> 5 | G6: =IF(C6=0,0,(D6+E6+F6)/(C6*3)) -> 1
B7: Configuración, Sucursales e Integraciones | C7: =COUNTIF('MATRIZ COMPLETA'!$C$4:$C$134,B7) -> 4 | D7: =COUNTIFS('MATRIZ COMPLETA'!$C$4:$C$134,B7,'MATRIZ COMPLETA'!$E$4:$E$134,"<>") -> 4 | E7: =COUNTIFS('MATRIZ COMPLETA'!$C$4:$C$134,B7,'MATRIZ COMPLETA'!$F$4:$F$134,"<>") -> 4 | F7: =COUNTIFS('MATRIZ COMPLETA'!$C$4:$C$134,B7,'MATRIZ COMPLETA'!$H$4:$H$134,"<>") -> 4 | G7: =IF(C7=0,0,(D7+E7+F7)/(C7*3)) -> 1
B8: Gestión de Mesas y Salón | C8: =COUNTIF('MATRIZ COMPLETA'!$C$4:$C$134,B8) -> 9 | D8: =COUNTIFS('MATRIZ COMPLETA'!$C$4:$C$134,B8,'MATRIZ COMPLETA'!$E$4:$E$134,"<>") -> 9 | E8: =COUNTIFS('MATRIZ COMPLETA'!$C$4:$C$134,B8,'MATRIZ COMPLETA'!$F$4:$F$134,"<>") -> 9 | F8: =COUNTIFS('MATRIZ COMPLETA'!$C$4:$C$134,B8,'MATRIZ COMPLETA'!$H$4:$H$134,"<>") -> 9 | G8: =IF(C8=0,0,(D8+E8+F8)/(C8*3)) -> 1
B9: Catálogo, Menú, Precios y Disponibilidad | C9: =COUNTIF('MATRIZ COMPLETA'!$C$4:$C$134,B9) -> 6 | D9: =COUNTIFS('MATRIZ COMPLETA'!$C$4:$C$134,B9,'MATRIZ COMPLETA'!$E$4:$E$134,"<>") -> 6 | E9: =COUNTIFS('MATRIZ COMPLETA'!$C$4:$C$134,B9,'MATRIZ COMPLETA'!$F$4:$F$134,"<>") -> 6 | F9: =COUNTIFS('MATRIZ COMPLETA'!$C$4:$C$134,B9,'MATRIZ COMPLETA'!$H$4:$H$134,"<>") -> 6 | G9: =IF(C9=0,0,(D9+E9+F9)/(C9*3)) -> 1
B10: Gestión de Órdenes | C10: =COUNTIF('MATRIZ COMPLETA'!$C$4:$C$134,B10) -> 8 | D10: =COUNTIFS('MATRIZ COMPLETA'!$C$4:$C$134,B10,'MATRIZ COMPLETA'!$E$4:$E$134,"<>") -> 8 | E10: =COUNTIFS('MATRIZ COMPLETA'!$C$4:$C$134,B10,'MATRIZ COMPLETA'!$F$4:$F$134,"<>") -> 8 | F10: =COUNTIFS('MATRIZ COMPLETA'!$C$4:$C$134,B10,'MATRIZ COMPLETA'!$H$4:$H$134,"<>") -> 8 | G10: =IF(C10=0,0,(D10+E10+F10)/(C10*3)) -> 1
B11: Pantallas de Cocina (KDS) | C11: =COUNTIF('MATRIZ COMPLETA'!$C$4:$C$134,B11) -> 7 | D11: =COUNTIFS('MATRIZ COMPLETA'!$C$4:$C$134,B11,'MATRIZ COMPLETA'!$E$4:$E$134,"<>") -> 7 | E11: =COUNTIFS('MATRIZ COMPLETA'!$C$4:$C$134,B11,'MATRIZ COMPLETA'!$F$4:$F$134,"<>") -> 7 | F11: =COUNTIFS('MATRIZ COMPLETA'!$C$4:$C$134,B11,'MATRIZ COMPLETA'!$H$4:$H$134,"<>") -> 7 | G11: =IF(C11=0,0,(D11+E11+F11)/(C11*3)) -> 1
B12: Enrutamiento Central de Pedidos | C12: =COUNTIF('MATRIZ COMPLETA'!$C$4:$C$134,B12) -> 4 | D12: =COUNTIFS('MATRIZ COMPLETA'!$C$4:$C$134,B12,'MATRIZ COMPLETA'!$E$4:$E$134,"<>") -> 4 | E12: =COUNTIFS('MATRIZ COMPLETA'!$C$4:$C$134,B12,'MATRIZ COMPLETA'!$F$4:$F$134,"<>") -> 4 | F12: =COUNTIFS('MATRIZ COMPLETA'!$C$4:$C$134,B12,'MATRIZ COMPLETA'!$H$4:$H$134,"<>") -> 4 | G12: =IF(C12=0,0,(D12+E12+F12)/(C12*3)) -> 1
B13: Gestión de Pagos (POS y Backoffice) | C13: =COUNTIF('MATRIZ COMPLETA'!$C$4:$C$134,B13) -> 11 | D13: =COUNTIFS('MATRIZ COMPLETA'!$C$4:$C$134,B13,'MATRIZ COMPLETA'!$E$4:$E$134,"<>") -> 11 | E13: =COUNTIFS('MATRIZ COMPLETA'!$C$4:$C$134,B13,'MATRIZ COMPLETA'!$F$4:$F$134,"<>") -> 11 | F13: =COUNTIFS('MATRIZ COMPLETA'!$C$4:$C$134,B13,'MATRIZ COMPLETA'!$H$4:$H$134,"<>") -> 11 | G13: =IF(C13=0,0,(D13+E13+F13)/(C13*3)) -> 1
B14: Compras y Proveedores | C14: =COUNTIF('MATRIZ COMPLETA'!$C$4:$C$134,B14) -> 5 | D14: =COUNTIFS('MATRIZ COMPLETA'!$C$4:$C$134,B14,'MATRIZ COMPLETA'!$E$4:$E$134,"<>") -> 5 | E14: =COUNTIFS('MATRIZ COMPLETA'!$C$4:$C$134,B14,'MATRIZ COMPLETA'!$F$4:$F$134,"<>") -> 5 | F14: =COUNTIFS('MATRIZ COMPLETA'!$C$4:$C$134,B14,'MATRIZ COMPLETA'!$H$4:$H$134,"<>") -> 5 | G14: =IF(C14=0,0,(D14+E14+F14)/(C14*3)) -> 1
B15: Inventarios y Recetas | C15: =COUNTIF('MATRIZ COMPLETA'!$C$4:$C$134,B15) -> 11 | D15: =COUNTIFS('MATRIZ COMPLETA'!$C$4:$C$134,B15,'MATRIZ COMPLETA'!$E$4:$E$134,"<>") -> 11 | E15: =COUNTIFS('MATRIZ COMPLETA'!$C$4:$C$134,B15,'MATRIZ COMPLETA'!$F$4:$F$134,"<>") -> 11 | F15: =COUNTIFS('MATRIZ COMPLETA'!$C$4:$C$134,B15,'MATRIZ COMPLETA'!$H$4:$H$134,"<>") -> 11 | G15: =IF(C15=0,0,(D15+E15+F15)/(C15*3)) -> 1
B16: Reservaciones y Lista de Espera | C16: =COUNTIF('MATRIZ COMPLETA'!$C$4:$C$134,B16) -> 8 | D16: =COUNTIFS('MATRIZ COMPLETA'!$C$4:$C$134,B16,'MATRIZ COMPLETA'!$E$4:$E$134,"<>") -> 8 | E16: =COUNTIFS('MATRIZ COMPLETA'!$C$4:$C$134,B16,'MATRIZ COMPLETA'!$F$4:$F$134,"<>") -> 8 | F16: =COUNTIFS('MATRIZ COMPLETA'!$C$4:$C$134,B16,'MATRIZ COMPLETA'!$H$4:$H$134,"<>") -> 8 | G16: =IF(C16=0,0,(D16+E16+F16)/(C16*3)) -> 1
... B21: Fidelización, CRM y Marketing | C21: =COUNTIF('MATRIZ COMPLETA'!$C$4:$C$134,B21) -> 9 | D21: =COUNTIFS('MATRIZ COMPLETA'!$C$4:$C$134,B21,'MATRIZ COMPLETA'!$E$4:$E$134,"<>") -> 9 | E21: =COUNTIFS('MATRIZ COMPLETA'!$C$4:$C$134,B21,'MATRIZ COMPLETA'!$F$4:$F$134,"<>") -> 9 | F21: =COUNTIFS('MATRIZ COMPLETA'!$C$4:$C$134,B21,'MATRIZ COMPLETA'!$H$4:$H$134,"<>") -> 9 | G21: =IF(C21=0,0,(D21+E21+F21)/(C21*3)) -> 1
B22: TOTAL | C22: =SUM(C5:C21) -> 131 | D22: =SUM(D5:D21) -> 131 | E22: =SUM(E5:E21) -> 131 | F22: =SUM(F5:F21) -> 131 | G22: =IF(C22=0,0,(D22+E22+F22)/(C22*3)) -> 1
B25: INDICADORES CLAVE | E25: ESTADO DE LA LÍNEA BASE
B26: KPI | C26: Valor | E26: Aspecto | F26: Estado | G26: Comentario
B27: Total RF | C27: =COUNTA('MATRIZ COMPLETA'!A4:A134) -> 131 | E27: Trazabilidad RF ↔ CU | F27: ✅ Documentado | G27: 131/131 vínculos
B28: RF base v1.0 normalizados | C28: =SUM(MÓDULOS!D4:D20) -> 101 | E28: Trazabilidad RF ↔ RNF | F28: ✅ Documentado | G28: 783 vínculos aplicables
B29: RF complementarios v2.0 | C29: =SUM(MÓDULOS!E4:E20) -> 30 | E29: Trazabilidad RF ↔ CP | F29: 🧪 Planificado | G29: 131 CP base; ejecución pendiente
B30: CU documentados | C30: =COUNTA('MATRIZ COMPLETA'!E4:E134) -> 131 | E30: Trazabilidad RF ↔ BPMN | F30: ✅ Documentado | G30: 131/131 RF vinculados a 17 procesos
B31: RNF definidos | C31: =COUNTA('CATÁLOGO RNF'!A4:A25) -> 22 | E31: RF complementarios v2.0 | F31: ⚠ Validar brecha v2.0 | G31: 30 RF requieren aprobación de stakeholders
B32: CP base planificados | C32: =COUNTA('RF → CP'!C4:C134) -> 131 | E32: Implementación del software | F32: ⏳ Pendiente | G32: La matriz documenta alcance; no implica implementación
B33: Módulos | C33: =COUNTA(MÓDULOS!A4:A20) -> 17 | E33: QA / UAT | F33: ⏳ Pendiente | G33: Definir casos detallados y ejecutar pruebas
B34: Enlaces RF → BPMN | C34: =COUNTA('RF → BPMN'!A4:A134) -> 131 | E34: Línea base final | F34: ⏳ Pendiente | G34: Cerrar riesgos/decisiones de la hoja PENDIENTES RUP
B35: Cobertura documental global | C35: =AVERAGE(G5:G21) -> 1

Sheet RF → BPMN
A1: TRAZABILIDAD — RF / CU ↔ PROCESOS BPMN
A2: Cada requerimiento está vinculado al proceso BPMN v2.0 de su módulo
A3: ID RF | B3: ID CU | C3: Módulo | D3: ID Proceso BPMN | E3: Proceso | F3: Actividad vinculada | G3: Carril / Actor | H3: Tipo BPMN | I3: Estado | J3: Observaciones
A4: RF-AUTH-001-BASICO | B4: CU-AUTH-001-BASICO | C4: Autenticación y Control de Acceso | D4: BPMN-AUTH-001 | E4: Proceso BPMN — Autenticación y Control de Acceso | F4: Inicio de sesión con usuario y contraseña | G4: Todos los roles del sistema | H4: User Task | I4: ✅ Documentado v2.0 | J4: Actividad equivalente/abreviada en el diagrama BPMN v2.0.
A5: RF-AUTH-002-BASICO | B5: CU-AUTH-002-BASICO | C5: Autenticación y Control de Acceso | D5: BPMN-AUTH-001 | E5: Proceso BPMN — Autenticación y Control de Acceso | F5: Recuperación de contraseña vía correo | G5: Todos los roles | H5: User Task | I5: ✅ Documentado v2.0 | J5: Actividad equivalente/abreviada en el diagrama BPMN v2.0.
A6: RF-AUTH-003-PREMIUM | B6: CU-AUTH-003-PREMIUM | C6: Autenticación y Control de Acceso | D6: BPMN-AUTH-001 | E6: Proceso BPMN — Autenticación y Control de Acceso | F6: Autenticación de dos factores (2FA) | G6: Administrador | H6: User/Service Task + Message | I6: ✅ Documentado v2.0 | J6: Actividad equivalente/abreviada en el diagrama BPMN v2.0.
A7: RF-AUTH-004-PREMIUM | B7: CU-AUTH-004-PREMIUM | C7: Autenticación y Control de Acceso | D7: BPMN-AUTH-001 | E7: Proceso BPMN — Autenticación y Control de Acceso | F7: Códigos de respaldo de un solo uso | G7: Administrador | H7: User Task | I7: ✅ Documentado v2.0 | J7: Actividad equivalente/abreviada en el diagrama BPMN v2.0.
A8: RF-AUTH-005-PREMIUM | B8: CU-AUTH-005-PREMIUM | C8: Autenticación y Control de Acceso | D8: BPMN-AUTH-001 | E8: Proceso BPMN — Autenticación y Control de Acceso | F8: Bitácora de auditoría de inicios de sesión | G8: Administrador | H8: User Task | I8: ✅ Documentado v2.0 | J8: Actividad equivalente/abreviada en el diagrama BPMN v2.0.
A9: RF-AUTH-006-GOLD | B9: CU-AUTH-006-GOLD | C9: Autenticación y Control de Acceso | D9: BPMN-AUTH-001 | E9: Proceso BPMN — Autenticación y Control de Acceso | F9: Autenticación biométrica (WebAuthn/FIDO2) | G9: Administrador | H9: User/Service Task + Message | I9: ✅ Documentado v2.0 | J9: Actividad equivalente/abreviada en el diagrama BPMN v2.0.
A10: RF-AUTH-007-GOLD | B10: CU-AUTH-007-GOLD | C10: Autenticación y Control de Acceso | D10: BPMN-AUTH-001 | E10: Proceso BPMN — Autenticación y Control de Acceso | F10: Soporte de llave de seguridad física (Hardware Key) | G10: Administrador | H10: User Task | I10: ✅ Documentado v2.0 | J10: Actividad equivalente/abreviada en el diagrama BPMN v2.0.
A11: RF-AUTH-008-GOLD | B11: CU-AUTH-008-GOLD | C11: Autenticación y Control de Acceso | D11: BPMN-AUTH-001 | E11: Proceso BPMN — Autenticación y Control de Acceso | F11: Gestión de dispositivos confiables | G11: Administrador | H11: User Task | I11: ✅ Documentado v2.0 | J11: Actividad equivalente/abreviada en el diagrama BPMN v2.0.
A12: RF-AUTH-009 | B12: CU-AUTH-009 | C12: Autenticación y Control de Acceso | D12: BPMN-AUTH-001 | E12: Proceso BPMN — Autenticación y Control de Acceso | F12: Expiración de sesión por inactividad | G12: Todos los roles | H12: Service Task | I12: ✅ Documentado v2.0 | J12: Actividad equivalente/abreviada en el diagrama BPMN v2.0.
A13: RF-REG-001-BASICO | B13: CU-REG-001-BASICO | C13: Registro y Gestión de Personal | D13: BPMN-REG-001 | E13: Proceso BPMN — Registro y Gestión de Personal | F13: Registro de datos personales del empleado | G13: Administrador | H13: User Task | I13: ✅ Documentado v2.0 | J13: Actividad equivalente/abreviada en el diagrama BPMN v2.0.
A14: RF-REG-002-BASICO | B14: CU-REG-002-BASICO | C14: Registro y Gestión de Personal | D14: BPMN-REG-001 | E14: Proceso BPMN — Registro y Gestión de Personal | F14: Control de acceso administrativo único | G14: Administrador | H14: User Task | I14: ✅ Documentado v2.0 | J14: Actividad equivalente/abreviada en el diagrama BPMN v2.0.
... A134: RF-CFG-004 | B134: CU-CFG-004 | C134: Configuración, Sucursales e Integraciones | D134: BPMN-CFG-001 | E134: Proceso BPMN — Configuración, Sucursales e Integraciones | F134: Plantillas de notificación y canales | G134: Administrador | H134: User Task | I134: ✅ Documentado v2.0 | J134: Actividad equivalente/abreviada en el diagrama BPMN v2.0.

Sheet CATÁLOGO RNF
A1: CATÁLOGO DE REQUERIMIENTOS NO FUNCIONALES
A2: 22 RNF consolidados de la SRS v2.0 · Clasificación ISO/IEC 25010 orientativa
A3: ID RNF | B3: Nombre / Categoría | C3: Categoría ISO/IEC 25010 | D3: Descripción | E3: Prioridad Propuesta | F3: Estado | G3: Observaciones
A4: RNF-001 | B4: Rendimiento | C4: Eficiencia de desempeño | D4: El sistema deberá procesar y reflejar una orden de mesero en la pantalla de cocina en menos de 5 segundos. Las consultas de dashboards deberán responder en menos de 3 segundos con hasta 50 usuarios concurrentes. | E4: Alta | F4: ⏳ Pendiente | G4: Prioridad propuesta para planificación; validar con arquitectura, negocio y QA.
A5: RNF-002 | B5: Seguridad | C5: Seguridad | D5: Las contraseñas deberán almacenarse con Argon2id preferentemente (o bcrypt/scrypt/PBKDF2 aprobados), nunca con hashes rápidos de propósito general. Los datos sensibles viajarán sobre TLS 1.2+ (TLS 1.3 preferido), los secretos se gestionarán fuera del código y la autorización se aplicará por rol y sucursal. | E5: Alta | F5: ⏳ Pendiente | G5: Prioridad propuesta para planificación; validar con arquitectura, negocio y QA.
A6: RNF-003 | B6: Disponibilidad | C6: Fiabilidad | D6: El sistema deberá estar disponible el 99.5% del tiempo en horario de operación del restaurante, con degradación controlada (modo offline básico de POS) ante pérdida de conectividad. | E6: Alta | F6: ⏳ Pendiente | G6: Prioridad propuesta para planificación; validar con arquitectura, negocio y QA.
A7: RNF-004 | B7: Usabilidad | C7: Capacidad de interacción / Usabilidad | D7: Las interfaces táctiles deberán priorizar tareas frecuentes con mínima navegación, mensajes claros y objetivos táctiles adecuados. El personal operativo deberá completar los flujos básicos con una capacitación objetivo menor a 1 hora y sin depender de manuales extensos. | E7: Media | F7: ⏳ Pendiente | G7: Prioridad propuesta para planificación; validar con arquitectura, negocio y QA.
A8: RNF-005 | B8: Escalabilidad | C8: Flexibilidad / Eficiencia de desempeño | D8: El sistema deberá soportar el crecimiento de un restaurante individual a una cadena multi-sucursal sin rediseño de arquitectura, incluyendo hasta 100 usuarios concurrentes por sucursal. | E8: Media | F8: ⏳ Pendiente | G8: Prioridad propuesta para planificación; validar con arquitectura, negocio y QA.
A9: RNF-006 | B9: Mantenibilidad | C9: Mantenibilidad | D9: El código deberá seguir un estándar de arquitectura modular (por dominio: mesas, órdenes, pagos, inventario, RRHH, CRM) que permita evolucionar cada módulo de forma independiente. | E9: Media | F9: ⏳ Pendiente | G9: Prioridad propuesta para planificación; validar con arquitectura, negocio y QA.
A10: RNF-007 | B10: Interoperabilidad | C10: Compatibilidad | D10: El sistema deberá integrarse mediante API con proveedores externos: FEL/SAT, pasarelas de pago, WhatsApp Business, agregadores de delivery (Uber Eats, PedidosYa) y dispositivos biométricos. | E10: Alta | F10: ⏳ Pendiente | G10: Prioridad propuesta para planificación; validar con arquitectura, negocio y QA.
A11: RNF-008 | B11: Sincronización en Tiempo Real | C11: Eficiencia de desempeño / Compatibilidad | D11: Los módulos de Mesas, Órdenes, Cocina (KDS) y Pagos deberán mantener sincronización en tiempo real (WebSockets) entre todos los dispositivos conectados. | E11: Alta | F11: ⏳ Pendiente | G11: Prioridad propuesta para planificación; validar con arquitectura, negocio y QA.
A12: RNF-009 | B12: Cumplimiento Normativo | C12: Adecuación funcional / Seguridad | D12: La facturación electrónica deberá cumplir la normativa FEL aplicable y conservar los identificadores/respuestas necesarios para auditoría. Otros requisitos legales o de privacidad deberán validarse con el responsable legal/contable del cliente antes de producción. | E12: Alta | F12: ⏳ Pendiente | G12: Prioridad propuesta para planificación; validar con arquitectura, negocio y QA.
A13: RNF-010 | B13: Auditabilidad | C13: Seguridad | D13: Toda transacción crítica (pago, anulación, descuento, cambio de inventario) deberá quedar registrada con usuario, fecha/hora y detalle, sin posibilidad de edición posterior. | E13: Alta | F13: ⏳ Pendiente | G13: Prioridad propuesta para planificación; validar con arquitectura, negocio y QA.
A14: RNF-011 | B14: Integridad e Idempotencia | C14: Fiabilidad | D14: Las operaciones críticas de creación de orden, cobro, reembolso, cierre e integración deberán tolerar reintentos sin duplicar el efecto. Se usarán transacciones y claves idempotentes cuando corresponda. | E14: Alta | F14: ⏳ Pendiente | G14: Prioridad propuesta para planificación; validar con arquitectura, negocio y QA.
... A25: RNF-022 | B25: Segregación de Datos Multi-sucursal | C25: Seguridad | D25: Los usuarios y terminales deberán acceder únicamente a las sucursales autorizadas. Reportes consolidados requerirán permiso explícito y toda transacción deberá conservar la sucursal de origen. | E25: Alta | F25: ⏳ Pendiente | G25: Prioridad propuesta para planificación; validar con arquitectura, negocio y QA.

Sheet MÓDULOS
A1: CATÁLOGO DE MÓDULOS Y COBERTURA FUNCIONAL
A2: 17 módulos · 101 RF base + 30 RF complementarios v2.0 = 131 RF
A3: Código | B3: Módulo / Subsistema | C3: Total RF | D3: RF Base v1.0 | E3: RF Brecha v2.0 | F3: Prioridad Alta | G3: Prioridad Media | H3: Prioridad Baja | I3: Proceso BPMN | J3: Cobertura Documental
A4: AUTH | B4: Autenticación y Control de Acceso | C4: 12 | D4: 9 | E4: 3 | F4: 6 | G4: 4 | H4: 2 | I4: BPMN-AUTH-001 | J4: ✅ 100% trazabilidad documental
A5: REG | B5: Registro y Gestión de Personal | C5: 5 | D5: 5 | E5: 0 | F5: 2 | G5: 3 | H5: 0 | I5: BPMN-REG-001 | J5: ✅ 100% trazabilidad documental
A6: CFG | B6: Configuración, Sucursales e Integraciones | C6: 4 | D6: 0 | E6: 4 | F6: 3 | G6: 1 | H6: 0 | I6: BPMN-CFG-001 | J6: ✅ 100% trazabilidad documental
A7: MESA | B7: Gestión de Mesas y Salón | C7: 9 | D7: 9 | E7: 0 | F7: 3 | G7: 5 | H7: 1 | I7: BPMN-MESA-001 | J7: ✅ 100% trazabilidad documental
A8: CAT | B8: Catálogo, Menú, Precios y Disponibilidad | C8: 6 | D8: 0 | E8: 6 | F8: 4 | G8: 2 | H8: 0 | I8: BPMN-CAT-001 | J8: ✅ 100% trazabilidad documental
A9: ORD | B9: Gestión de Órdenes | C9: 8 | D9: 6 | E9: 2 | F9: 4 | G9: 3 | H9: 1 | I9: BPMN-ORD-001 | J9: ✅ 100% trazabilidad documental
A10: COC | B10: Pantallas de Cocina (KDS) | C10: 7 | D10: 7 | E10: 0 | F10: 4 | G10: 2 | H10: 1 | I10: BPMN-COC-001 | J10: ✅ 100% trazabilidad documental
A11: ROUT | B11: Enrutamiento Central de Pedidos | C11: 4 | D11: 4 | E11: 0 | F11: 3 | G11: 1 | H11: 0 | I11: BPMN-ROUT-001 | J11: ✅ 100% trazabilidad documental
A12: PAG | B12: Gestión de Pagos (POS y Backoffice) | C12: 11 | D12: 8 | E12: 3 | F12: 8 | G12: 3 | H12: 0 | I12: BPMN-PAG-001 | J12: ✅ 100% trazabilidad documental
A13: PUR | B13: Compras y Proveedores | C13: 5 | D13: 0 | E13: 5 | F13: 4 | G13: 1 | H13: 0 | I13: BPMN-PUR-001 | J13: ✅ 100% trazabilidad documental
A14: INV | B14: Inventarios y Recetas | C14: 11 | D14: 7 | E14: 4 | F14: 7 | G14: 4 | H14: 0 | I14: BPMN-INV-001 | J14: ✅ 100% trazabilidad documental
A15: RES | B15: Reservaciones y Lista de Espera | C15: 8 | D15: 7 | E15: 1 | F15: 4 | G15: 4 | H15: 0 | I15: BPMN-RES-001 | J15: ✅ 100% trazabilidad documental
... A20: CRM | B20: Fidelización, CRM y Marketing | C20: 9 | D20: 8 | E20: 1 | F20: 3 | G20: 4 | H20: 2 | I20: BPMN-CRM-001 | J20: ✅ 100% trazabilidad documental

Sheet PENDIENTES RUP
A1: RIESGOS, DECISIONES ABIERTAS Y ARTEFACTOS RUP
A2: Pendientes de validación para completar la línea base y preparar desarrollo / QA / operación
A4: RIESGOS Y DECISIONES ABIERTAS
A5: ID | B5: Riesgo / decisión | C5: Impacto | D5: Acción requerida | E5: Estado
A6: R-01 | B6: Proveedor FEL y contrato/API definitivo no especificados | C6: Alto | D6: Seleccionar proveedor, sandbox y criterios de contingencia antes de pruebas integrales. | E6: ⏳ Pendiente
A7: R-02 | B7: Pasarela/terminal de pago y capacidades de reverso/tokenización por definir | C7: Alto | D7: Definir proveedor, certificación de hardware y flujo de conciliación. | E7: ⏳ Pendiente
A8: R-03 | B8: Matriz comercial Básico/Premium/Gold incompleta para módulos distintos de AUTH/REG | C8: Medio | D8: Aprobar matriz de capacidades por plan y reflejarla en licenciamiento/configuración. | E8: ⏳ Pendiente
A9: R-04 | B9: Operación offline no delimitada por tipo de pago/venta | C9: Alto | D9: Acordar funciones permitidas, límites, seguridad y reconciliación. | E9: ⏳ Pendiente
A10: R-05 | B10: Compatibilidad de impresoras, cajones, KDS, biometría y dispositivos | C10: Medio | D10: Crear matriz de hardware certificado y laboratorio de pruebas. | E10: ⏳ Pendiente
A11: R-06 | B11: Migración de datos desde sistemas/hojas existentes no especificada | C11: Medio | D11: Inventariar fuentes, calidad, volumen y reglas de limpieza/carga. | E11: ⏳ Pendiente
A12: R-07 | B12: Volumen esperado de órdenes, sucursales y retención histórica no cuantificado | C12: Medio | D12: Definir escenarios de capacidad para dimensionamiento y pruebas de rendimiento. | E12: ⏳ Pendiente
A13: R-08 | B13: Políticas de privacidad, conservación y consentimiento pendientes de aprobación formal | C13: Alto | D13: Validar con responsables legal/administrativo antes de producción. | E13: ⏳ Pendiente
A15: ARTEFACTOS RUP / INGENIERÍA DE SOFTWARE
A16: Artefacto | B16: Estado | C16: Cobertura / Acción | D16: Referencia
A17: Especificación de Requerimientos de Software (SRS) | B17: ✅ Completo v2.0 | C17: 131 RF · 22 RNF · 17 módulos | D17: Requerimientos_Software_Restaurante_V2_Profesional.docx
A18: Especificación de Casos de Uso | B18: ✅ Completo v2.0 | C18: 131 CU alineados con RF | D18: Casos_De_Uso_Restaurante_V2_Profesional.docx
A19: Diagramas BPMN | B19: ✅ Completo v2.0 | C19: 17 procesos/módulos con trazabilidad a RF/CU | D19: Diagramas_BPMN_Restaurante_V2_Profesional.docx
A20: Diagramas UML de Casos de Uso | B20: ✅ Completo v2.0 | C20: 17 diagramas UML + 131 diagramas de actividad | D20: Diagramas_Casos_De_Uso_Restaurante_V2_Profesional.docx
A21: Matriz de Trazabilidad RUP | B21: ✅ Actualizada | C21: RF ↔ CU ↔ RNF ↔ CP ↔ BPMN | D21: Matriz_Trazabilidad_RUP_V2_Completa.xlsx
A22: Casos de prueba detallados | B22: 🧪 Planificados | C22: 131 CP base creados; falta detallar escenarios y ejecutar | D22: Pendiente fase QA
A23: Modelo lógico/físico de datos | B23: ⏳ Pendiente | C23: Derivar del modelo conceptual; documentar índices, restricciones y auditoría | D23: Pendiente
A24: ADRs de arquitectura | B24: ⏳ Pendiente | C24: Formalizar stack, mensajería, caché, offline, seguridad y despliegue | D24: Pendiente
A25: Contrato de APIs | B25: ⏳ Pendiente | C25: Endpoints/eventos, esquemas, errores, autenticación, idempotencia y versionado | D25: Pendiente
A26: Matriz de roles y permisos | B26: ⚠ Validación requerida | C26: RBAC especificado en RF-AUTH-010; falta aprobación formal por rol/sucursal | D26: Pendiente aprobación
A27: Matriz de planes comerciales | B27: ⚠ Validación requerida | C27: Definir capacidades Básico/Premium/Gold para todos los módulos | D27: Pendiente aprobación
... A29: Runbook de operación | B29: ⏳ Pendiente | C29: Monitoreo, incidentes, respaldo, restauración, secretos y escalamiento | D29: Pendiente
